Metadata-Version: 2.1
Name: CobwebIT
Version: 1.0.0
Summary: This is a Complex of random things
Author: Francisek s
Classifier: Programming Language :: Python :: 3
Classifier: License :: OSI Approved :: MIT License
Classifier: Operating System :: OS Independent
Requires-Python: >=3.12
